Circuits/Combinational-Logic/Arithmetic/adder32.v
module adder32(

    input [31:0] a,
    input [31:0] b, 
    input        cin,
    output       cout,
    output [31:0] sum


);

    wire [7:0] c_w;


    adder4 inst0(.a(a[3:0]),   .b(b[3:0]),  . cin(cin),     .sum(sum[3:0]),   .cout(c_w[0]));
    adder4 inst1(.a(a[7:4]),   .b(b[7:4]),   .cin(c_w[0]),  .sum(sum[7:4]),   .cout(c_w[1]));
    adder4 inst2(.a(a[11:8]),  .b(b[11:8]),  .cin(c_w[1]),  .sum(sum[11:8]),  .cout(c_w[2]) );
    adder4 inst3(.a(a[15:12]), .b(b[15:12]), .cin(c_w[2]),  .sum(sum[15:12]), .cout(c_w[3]));
    adder4 inst4(.a(a[19:16]), .b(b[19:16]), .cin(c_w[3]),  .sum(sum[19:16]), .cout(c_w[4]));
    adder4 inst5(.a(a[23:20]), .b(b[23:20]), .cin(c_w[4]),  .sum(sum[23:20]), .cout(c_w[5]));
    adder4 inst6(.a(a[27:24]), .b(b[27:24]), .cin(c_w[5]),  .sum(sum[27:24]), .cout(c_w[6]));
    adder4 inst7(.a(a[31:28]), .b(b[31:28]), .cin(c_w[6]),  .sum(sum[31:28]), .cout(cout));
    

endmodule


module adder4(

    input [3:0] a,
    input [3:0] b,
    input       cin,
    output      cout,
    output [3:0] sum


);

    // wire c1, c2, c3;

    // adder1 inst0(.a(a[0]), .b(b[0]), .cin(cin), .sum(sum[0]), .cout(c1));
    // adder1 inst1(.a(a[1]), .b(b[1]), .cin(c1), .sum(sum[1]), .cout(c2));
    // adder1 inst2(.a(a[2]), .b(b[2]), .cin(c2), .sum(sum[2]), .cout(c3));
    // adder1 inst3(.a(a[3]), .b(b[3]), .cin(c3), .sum(sum[3]), .cout(cout));

    
    wire [4:0] c_w;
    assign c_w[0] = cin;

    adder1 inst0(.a(a[0]), .b(b[0]), .cin(c_w[0]), .sum(sum[0]), .cout(c_w[1]));
    adder1 inst1(.a(a[1]), .b(b[1]), .cin(c_w[1]), .sum(sum[1]), .cout(c_w[2]));
    adder1 inst2(.a(a[2]), .b(b[2]), .cin(c_w[2]), .sum(sum[2]), .cout(c_w[3]));
    adder1 inst3(.a(a[3]), .b(b[3]), .cin(c_w[3]), .sum(sum[3]), .cout(c_w[4]));

    assign cout = c_w[4];
    

endmodule

module adder1(

    input a,
    input b,
    input cin,
    output cout,
    output sum

);

    assign {cout, sum} = a + b + cin;

endmodule

module tb;

    reg [31:0] a;
    reg [31:0] b;
    reg       cin;
    wire [31:0] sum;
    wire        cout;

    assign result_tb = a + b + cin;
    assign result    = {cout, sum};

    adder32 u0(.a(a), .b(b), .cin(cin), .cout(cout), .sum(sum));

    integer i;


    // initial begin
    //     $display("a\tb\tcin\tcout\tsum");
    //     $monitor("%b\t%b\t%b\t%b\t%b", a, b, cin, cout, sum, $time);

    // end

    initial begin   
        a = 0;
        b = 0;
        cin = 0;

        for (i = 0; i < 15; i = i + 1) begin
            #10
            a = $random;
            b = $random;
            cin= $random;
            
           #10
            
            if (result_tb == result)
                $display("PASSED");
            else
                $display("FAILED %d %d", result_tb, result);    
        end

        $finish;
    end 

    initial begin  

        $dumpfile("adder32.vcd");
        $dumpvars;


    end
endmodule

Circuits/Combinational-Logic/Arithmetic/adder32.vcd
$date
	Wed May 10 15:14:06 2023
$end
$version
	Icarus Verilog
$end
$timescale
	1s
$end
$scope module tb $end
$var wire 32 ! sum [31:0] $end
$var wire 1 " result_tb $end
$var wire 1 # result $end
$var wire 1 $ cout $end
$var reg 32 % a [31:0] $end
$var reg 32 & b [31:0] $end
$var reg 1 ' cin $end
$var integer 32 ( i [31:0] $end
$scope module u0 $end
$var wire 32 ) a [31:0] $end
$var wire 32 * b [31:0] $end
$var wire 1 ' cin $end
$var wire 32 + sum [31:0] $end
$var wire 1 $ cout $end
$var wire 8 , c_w [7:0] $end
$scope module inst0 $end
$var wire 4 - a [3:0] $end
$var wire 4 . b [3:0] $end
$var wire 1 ' cin $end
$var wire 4 / sum [3:0] $end
$var wire 1 0 cout $end
$var wire 5 1 c_w [4:0] $end
$scope module inst0 $end
$var wire 1 2 a $end
$var wire 1 3 b $end
$var wire 1 4 cin $end
$var wire 1 5 sum $end
$var wire 1 6 cout $end
$upscope $end
$scope module inst1 $end
$var wire 1 7 a $end
$var wire 1 8 b $end
$var wire 1 9 cin $end
$var wire 1 : sum $end
$var wire 1 ; cout $end
$upscope $end
$scope module inst2 $end
$var wire 1 < a $end
$var wire 1 = b $end
$var wire 1 > cin $end
$var wire 1 ? sum $end
$var wire 1 @ cout $end
$upscope $end
$scope module inst3 $end
$var wire 1 A a $end
$var wire 1 B b $end
$var wire 1 C cin $end
$var wire 1 D sum $end
$var wire 1 E cout $end
$upscope $end
$upscope $end
$scope module inst1 $end
$var wire 4 F a [3:0] $end
$var wire 4 G b [3:0] $end
$var wire 1 H cin $end
$var wire 4 I sum [3:0] $end
$var wire 1 J cout $end
$var wire 5 K c_w [4:0] $end
$scope module inst0 $end
$var wire 1 L a $end
$var wire 1 M b $end
$var wire 1 N cin $end
$var wire 1 O sum $end
$var wire 1 P cout $end
$upscope $end
$scope module inst1 $end
$var wire 1 Q a $end
$var wire 1 R b $end
$var wire 1 S cin $end
$var wire 1 T sum $end
$var wire 1 U cout $end
$upscope $end
$scope module inst2 $end
$var wire 1 V a $end
$var wire 1 W b $end
$var wire 1 X cin $end
$var wire 1 Y sum $end
$var wire 1 Z cout $end
$upscope $end
$scope module inst3 $end
$var wire 1 [ a $end
$var wire 1 \ b $end
$var wire 1 ] cin $end
$var wire 1 ^ sum $end
$var wire 1 _ cout $end
$upscope $end
$upscope $end
$scope module inst2 $end
$var wire 4 ` a [3:0] $end
$var wire 4 a b [3:0] $end
$var wire 1 b cin $end
$var wire 4 c sum [3:0] $end
$var wire 1 d cout $end
$var wire 5 e c_w [4:0] $end
$scope module inst0 $end
$var wire 1 f a $end
$var wire 1 g b $end
$var wire 1 h cin $end
$var wire 1 i sum $end
$var wire 1 j cout $end
$upscope $end
$scope module inst1 $end
$var wire 1 k a $end
$var wire 1 l b $end
$var wire 1 m cin $end
$var wire 1 n sum $end
$var wire 1 o cout $end
$upscope $end
$scope module inst2 $end
$var wire 1 p a $end
$var wire 1 q b $end
$var wire 1 r cin $end
$var wire 1 s sum $end
$var wire 1 t cout $end
$upscope $end
$scope module inst3 $end
$var wire 1 u a $end
$var wire 1 v b $end
$var wire 1 w cin $end
$var wire 1 x sum $end
$var wire 1 y cout $end
$upscope $end
$upscope $end
$scope module inst3 $end
$var wire 4 z a [3:0] $end
$var wire 4 { b [3:0] $end
$var wire 1 | cin $end
$var wire 4 } sum [3:0] $end
$var wire 1 ~ cout $end
$var wire 5 !" c_w [4:0] $end
$scope module inst0 $end
$var wire 1 "" a $end
$var wire 1 #" b $end
$var wire 1 $" cin $end
$var wire 1 %" sum $end
$var wire 1 &" cout $end
$upscope $end
$scope module inst1 $end
$var wire 1 '" a $end
$var wire 1 (" b $end
$var wire 1 )" cin $end
$var wire 1 *" sum $end
$var wire 1 +" cout $end
$upscope $end
$scope module inst2 $end
$var wire 1 ," a $end
$var wire 1 -" b $end
$var wire 1 ." cin $end
$var wire 1 /" sum $end
$var wire 1 0" cout $end
$upscope $end
$scope module inst3 $end
$var wire 1 1" a $end
$var wire 1 2" b $end
$var wire 1 3" cin $end
$var wire 1 4" sum $end
$var wire 1 5" cout $end
$upscope $end
$upscope $end
$scope module inst4 $end
$var wire 4 6" a [3:0] $end
$var wire 4 7" b [3:0] $end
$var wire 1 8" cin $end
$var wire 4 9" sum [3:0] $end
$var wire 1 :" cout $end
$var wire 5 ;" c_w [4:0] $end
$scope module inst0 $end
$var wire 1 <" a $end
$var wire 1 =" b $end
$var wire 1 >" cin $end
$var wire 1 ?" sum $end
$var wire 1 @" cout $end
$upscope $end
$scope module inst1 $end
$var wire 1 A" a $end
$var wire 1 B" b $end
$var wire 1 C" cin $end
$var wire 1 D" sum $end
$var wire 1 E" cout $end
$upscope $end
$scope module inst2 $end
$var wire 1 F" a $end
$var wire 1 G" b $end
$var wire 1 H" cin $end
$var wire 1 I" sum $end
$var wire 1 J" cout $end
$upscope $end
$scope module inst3 $end
$var wire 1 K" a $end
$var wire 1 L" b $end
$var wire 1 M" cin $end
$var wire 1 N" sum $end
$var wire 1 O" cout $end
$upscope $end
$upscope $end
$scope module inst5 $end
$var wire 4 P" a [3:0] $end
$var wire 4 Q" b [3:0] $end
$var wire 1 R" cin $end
$var wire 4 S" sum [3:0] $end
$var wire 1 T" cout $end
$var wire 5 U" c_w [4:0] $end
$scope module inst0 $end
$var wire 1 V" a $end
$var wire 1 W" b $end
$var wire 1 X" cin $end
$var wire 1 Y" sum $end
$var wire 1 Z" cout $end
$upscope $end
$scope module inst1 $end
$var wire 1 [" a $end
$var wire 1 \" b $end
$var wire 1 ]" cin $end
$var wire 1 ^" sum $end
$var wire 1 _" cout $end
$upscope $end
$scope module inst2 $end
$var wire 1 `" a $end
$var wire 1 a" b $end
$var wire 1 b" cin $end
$var wire 1 c" sum $end
$var wire 1 d" cout $end
$upscope $end
$scope module inst3 $end
$var wire 1 e" a $end
$var wire 1 f" b $end
$var wire 1 g" cin $end
$var wire 1 h" sum $end
$var wire 1 i" cout $end
$upscope $end
$upscope $end
$scope module inst6 $end
$var wire 4 j" a [3:0] $end
$var wire 4 k" b [3:0] $end
$var wire 1 l" cin $end
$var wire 4 m" sum [3:0] $end
$var wire 1 n" cout $end
$var wire 5 o" c_w [4:0] $end
$scope module inst0 $end
$var wire 1 p" a $end
$var wire 1 q" b $end
$var wire 1 r" cin $end
$var wire 1 s" sum $end
$var wire 1 t" cout $end
$upscope $end
$scope module inst1 $end
$var wire 1 u" a $end
$var wire 1 v" b $end
$var wire 1 w" cin $end
$var wire 1 x" sum $end
$var wire 1 y" cout $end
$upscope $end
$scope module inst2 $end
$var wire 1 z" a $end
$var wire 1 {" b $end
$var wire 1 |" cin $end
$var wire 1 }" sum $end
$var wire 1 ~" cout $end
$upscope $end
$scope module inst3 $end
$var wire 1 !# a $end
$var wire 1 "# b $end
$var wire 1 ## cin $end
$var wire 1 $# sum $end
$var wire 1 %# cout $end
$upscope $end
$upscope $end
$scope module inst7 $end
$var wire 4 &# a [3:0] $end
$var wire 4 '# b [3:0] $end
$var wire 1 (# cin $end
$var wire 4 )# sum [3:0] $end
$var wire 1 $ cout $end
$var wire 5 *# c_w [4:0] $end
$scope module inst0 $end
$var wire 1 +# a $end
$var wire 1 ,# b $end
$var wire 1 -# cin $end
$var wire 1 .# sum $end
$var wire 1 /# cout $end
$upscope $end
$scope module inst1 $end
$var wire 1 0# a $end
$var wire 1 1# b $end
$var wire 1 2# cin $end
$var wire 1 3# sum $end
$var wire 1 4# cout $end
$upscope $end
$scope module inst2 $end
$var wire 1 5# a $end
$var wire 1 6# b $end
$var wire 1 7# cin $end
$var wire 1 8# sum $end
$var wire 1 9# cout $end
$upscope $end
$scope module inst3 $end
$var wire 1 :# a $end
$var wire 1 ;# b $end
$var wire 1 <# cin $end
$var wire 1 =# sum $end
$var wire 1 ># cout $end
$upscope $end
$upscope $end
$upscope $end
$upscope $end
$enddefinitions $end
#0
$dumpvars
0>#
0=#
0<#
0;#
0:#
09#
08#
07#
06#
05#
04#
03#
02#
01#
00#
0/#
0.#
0-#
0,#
0+#
b0 *#
b0 )#
0(#
b0 '#
b0 &#
0%#
0$#
0##
0"#
0!#
0~"
0}"
0|"
0{"
0z"
0y"
0x"
0w"
0v"
0u"
0t"
0s"
0r"
0q"
0p"
b0 o"
0n"
b0 m"
0l"
b0 k"
b0 j"
0i"
0h"
0g"
0f"
0e"
0d"
0c"
0b"
0a"
0`"
0_"
0^"
0]"
0\"
0["
0Z"
0Y"
0X"
0W"
0V"
b0 U"
0T"
b0 S"
0R"
b0 Q"
b0 P"
0O"
0N"
0M"
0L"
0K"
0J"
0I"
0H"
0G"
0F"
0E"
0D"
0C"
0B"
0A"
0@"
0?"
0>"
0="
0<"
b0 ;"
0:"
b0 9"
08"
b0 7"
b0 6"
05"
04"
03"
02"
01"
00"
0/"
0."
0-"
0,"
0+"
0*"
0)"
0("
0'"
0&"
0%"
0$"
0#"
0""
b0 !"
0~
b0 }
0|
b0 {
b0 z
0y
0x
0w
0v
0u
0t
0s
0r
0q
0p
0o
0n
0m
0l
0k
0j
0i
0h
0g
0f
b0 e
0d
b0 c
0b
b0 a
b0 `
0_
0^
0]
0\
0[
0Z
0Y
0X
0W
0V
0U
0T
0S
0R
0Q
0P
0O
0N
0M
0L
b0 K
0J
b0 I
0H
b0 G
b0 F
0E
0D
0C
0B
0A
0@
0?
0>
0=
0<
0;
0:
09
08
07
06
05
04
03
02
b0 1
00
b0 /
b0 .
b0 -
bz0000000 ,
b0 +
b0 *
b0 )
b0 (
0'
b0 &
b0 %
0$
0#
0"
b0 !
$end
#10
1%"
14"
1$"
13"
1|
10"
bz0000100 ,
1d
1."
1:
1y
1+"
1D"
19
1w
1)"
1C"
16
1^
1n
b11000 e
1t
0x
b1111 !"
1&"
0/"
b10 ;"
1@"
1N"
1h"
18#
1=#
b110 /
1?
b1010 I
1T
b11 c
1i
b1001 }
0*"
b1110 9"
1I"
b1001 S"
1Y"
b10 m"
1x"
b11010010100111101001001110100110 !
b11010010100111101001001110100110 +
b1101 )#
1.#
13
1\
1l
1q
1v
1#"
1-"
1="
1L"
1f"
16#
1;#
1<
1Q
1f
1p
1""
1'"
1<"
1F"
1V"
1u"
1+#
14
b1 .
b1000 G
b1110 a
b101 {
b1001 7"
b1000 Q"
b1100 '#
b100 -
b10 F
b101 `
b11 z
b101 6"
b1 P"
b10 j"
b1 &#
b11 1
1'
b11000000100010010101111010000001 &
b11000000100010010101111010000001 *
b10010000101010011010100100100 %
b10010000101010011010100100100 )
#20
b1 (
#30
1$#
1##
1O
1~"
1N
1|"
1%"
b1 K
1H
0x"
1y"
1$"
10
1w"
b1111 !"
1|
1E
1t"
1d
1g"
1C
1r"
0x
1y
1^"
1d"
0?
1@
0D"
b1111 o"
1l"
1w
1]"
1b"
1#
1>
1r
0C"
bz0100101 ,
1T"
0D
0^
0s
1t
0Y"
1Z"
1_"
0}"
08#
15
b1 /
0:
b11111 1
1;
b111 I
1Y
b1 c
0n
b11100 e
1o
b1101 }
1/"
1?"
b0 ;"
0@"
b1001 9"
0I"
0c"
b1010 S"
1h"
b11110 U"
1i"
b1000 m"
0s"
b10111000101010011101000101110001 !
b10111000101010011101000101110001 +
b1011 )#
13#
1=
1B
0\
1g
0q
1("
1W"
1\"
1v"
1{"
06#
0;#
12
17
0<
1V
0f
1k
0'"
1,"
0<"
0F"
1["
1`"
1e"
1p"
0u"
10#
1:#
b1101 .
b0 G
b1011 a
b111 {
b1011 Q"
b110 k"
b0 '#
1"
b11 -
b110 F
b110 `
b101 z
b0 6"
b1111 P"
b1 j"
b1011 &#
b110101110010111101100001101 &
b110101110010111101100001101 *
b10110001111100000101011001100011 %
b10110001111100000101011001100011 )
#40
b10 (
#50
0|"
1x"
0y"
0w"
1s"
0t"
0r"
08#
0l"
07#
0T"
0^
13#
04#
0D"
0i"
0]
0)"
02#
0C"
0g"
1Y
0Z
0&"
1.#
0/#
1?"
0@"
1c"
0d"
0N
0X
0$"
03"
1M"
0-#
0w
0>"
0b"
0H
1T
0U
0|
00"
1J"
0(#
1s
0t
08"
0_"
0#
00
0S
0d
0."
1H"
0##
0n"
1$
0r
bz0000000 ,
0~
0]"
05
b1000 /
1D
b1111 1
0E
b111 I
1O
b0 K
0P
0i
0x
0y
0*"
0+"
b1100 ;"
1E"
0I"
b1001 9"
1N"
1h"
0}"
0~"
b1011 m"
1$#
b0 o"
0%#
b11 )#
0=#
b10000 *#
1>#
b110 c
1n
b0 e
0o
1%"
1/"
b1101 }
14"
b0 !"
05"
1Y"
b0 U"
0Z"
b111011111110011101011001111000 !
b111011111110011101011001111000 +
b1111 S"
1^"
03
18
0=
0B
1M
0g
0v
0("
1B"
1G"
0L"
0f"
1q"
0v"
0{"
1"#
1;#
07
1<
0k
0""
0,"
11"
1A"
0V"
0["
0p"
1u"
0"
b10 .
b1 G
b10 a
b101 {
b111 7"
b11 Q"
b1001 k"
b1000 '#
b101 -
b100 `
b1000 z
b10 6"
b1100 P"
b10 j"
b10001001001101110101001000010010 &
b10001001001101110101001000010010 *
b10110010110000101000010001100101 %
b10110010110000101000010001100101 )
#60
b11 (
#70
18#
17#
03#
14#
1^
12#
1]
b100 )#
0.#
1/#
0Y
1Z
1-#
1X
1(#
0T
1U
1n"
1S
0$#
1%#
b1000 I
0O
1P
1>"
1##
1N
18"
1~"
b1111 K
1H
1D"
1m
1~
1|"
bz1001001 ,
10
13"
1C"
0$
1?
b10 e
1j
1n
1*"
14"
15"
0x"
b11100 o"
1y"
b100 /
0D
b11111 1
1E
b1110 c
1x
b1011 }
0/"
b11000 !"
10"
b1011 9"
1?"
b1111 ;"
1@"
b1000001111110111011111010000100 !
b1000001111110111011111010000100 +
b1 m"
0}"
b111 *#
0>#
1=
1R
1W
1g
0l
1("
12"
0G"
0W"
1v"
1,#
11#
0;#
1A
0Q
0V
1f
1u
1,"
1<"
1F"
1V"
1z"
0+#
00#
0:#
b110 .
b111 G
b1 a
b1111 {
b11 7"
b10 Q"
b1011 k"
b11 '#
b1101 -
b0 F
b1101 `
b1100 z
b111 6"
b1101 P"
b110 j"
b0 &#
b111011001000111111000101110110 &
b111011001000111111000101110110 *
b110110101111100110100001101 %
b110110101111100110100001101 )
#80
b100 (
#90
1r"
1l"
1T"
0h"
1i"
1g"
0c"
1d"
08#
1b"
07#
0^
0^"
1_"
13#
04#
0]
1]"
02#
1Y
0Z
b0 S"
0Y"
1Z"
1.#
0/#
1i
1/"
0X
1X"
0-#
1h
1."
0?
1T
0U
b11111 U"
1R"
0(#
1b
0*"
1+"
b1011 )#
1=#
0>
0S
1w
0H"
1:"
0n"
bz0111011 ,
1J
1r
1)"
1<#
1:
b11011 1
0;
b1010 /
1D
b111 I
1O
0P
1s
1t
0E"
0I"
0N"
b11011 ;"
1O"
1s"
1}"
b1101 m"
1$#
b1101 o"
0%#
b10001 K
1_
b1111 e
1o
b1111 c
1x
0%"
b11110 !"
1&"
b100 }
04"
b10111101000000100100111101111010 !
b10111101000000100100111101111010 +
b10 9"
0?"
b1000 *#
19#
08
1B
0M
0R
0W
1\
1l
1q
0B"
1G"
1L"
0q"
1{"
0"#
0,#
01#
16#
1Q
1V
1[
1k
0u
1""
01"
0<"
0A"
1+#
10#
15#
b1100 .
b1000 G
b111 a
b1101 7"
b110 k"
b100 '#
b1110 F
b111 `
b101 z
b100 6"
b111 &#
b1000110001011011111011110001100 &
b1000110001011011111011110001100 *
b1110110110101000101011111101101 %
b1110110110101000101011111101101 )
#100
b101 (
#110
0>"
0O
08"
0/"
0N
0~
0X"
0."
0H
1^
0n
b1001 c
0s
14"
05"
b11110 U"
0R"
0$#
18#
0?
b1010 }
1*"
0+"
1I"
1x"
00
1]
0m
0r
03"
bz0100010 ,
0:"
0##
17#
0>
0)"
1H"
1w"
1$
1#
09
0E
0Y
b11000 K
1Z
0j
b1001 e
0o
00"
1N"
0O"
0Y"
0~"
03#
14#
1:
0;
b1000 I
0T
b0 !"
0&"
b1110 9"
0?"
b1110 ;"
1E"
b10 S"
1^"
b110 m"
0s"
b111 o"
1t"
b1100 )#
0.#
b11100 *#
1>#
b11000110001011101010100110001011 !
b11000110001011101010100110001011 +
b1011 /
15
06
13
0B
1W
0g
0l
0#"
0("
0-"
1B"
0L"
1W"
1a"
1f"
0{"
11#
1;#
02
17
0A
0Q
0f
0k
0""
1'"
0,"
1<"
1A"
1["
0`"
0e"
1p"
0z"
0+#
1:#
04
b101 .
b1100 G
b100 a
b1000 {
b111 7"
b1111 Q"
b10 k"
b1110 '#
1"
b110 -
b1100 F
b100 `
b10 z
b111 6"
b11 P"
b11 j"
b1110 &#
b1000 1
0'
b11100010111101111000010011000101 &
b11100010111101111000010011000101 *
b11100011001101110010010011000110 %
b11100011001101110010010011000110 )
#120
b110 (
#130
1>"
1g"
18"
1?
0c"
1d"
1~
1>
1X"
1b"
1Y
1x
1/"
04"
15"
1D"
13#
0:
1;
1n
1R"
1_"
1X
1r
1w
1)"
1."
13"
1C"
12#
0#
19
1m
bz0111010 ,
1:"
1]"
1O
b11100 K
1U
b101 I
0^
1o
0s
1t
1&"
b110 }
1*"
1+"
b11110 !"
10"
0?"
1@"
0I"
0^"
b1110 m"
1$#
b11110 *#
1/#
08#
b1100 /
05
b1110 1
16
b1010 c
0i
b1111 e
1j
b10 9"
0N"
b11111 ;"
1O"
0Y"
b11111 U"
1Z"
b1000 S"
1h"
b101110100000100110101001011100 !
b101110100000100110101001011100 +
b10 )#
0=#
18
1M
1R
0\
1l
0q
1#"
1("
1-"
02"
0="
0G"
0\"
1q"
1"#
1,#
06#
12
07
1Q
1f
1k
1""
1,"
11"
1K"
0V"
1e"
0p"
1+#
0:#
b111 .
b111 G
b10 a
b111 {
b10 7"
b1101 Q"
b1011 k"
b1011 '#
0"
b101 -
b1110 F
b111 `
b1111 z
b1111 6"
b1010 P"
b10 j"
b111 &#
b10111011110100100111001001110111 &
b10111011110100100111001001110111 *
b1110010101011111111011111100101 %
b1110010101011111111011111100101 )
#140
b111 (
#150
0]"
1Y"
0Z"
0X"
b11100 U"
0R"
0:"
1S
1-#
1/"
1N"
0O"
0O
1P
1(#
1."
0M"
1N
1]
1$"
1n"
17#
1+"
1I"
0J"
1H
1Z
0x
1|
0D"
0$#
1%#
14#
1#
09
1)"
0H"
0$
10
1X
0w
bz1101111 ,
1d
0C"
1##
12#
15
06
0?
1^
1i
0n
0%"
b11111 !"
1&"
0E"
0^"
b1 S"
0h"
0x"
18#
1=#
0>#
0:
b1 /
0D
b11100 1
1E
0T
b11111 K
1U
b1000 I
0Y
b101 c
1s
0t
b10111 e
1y
b100 }
0*"
b1101 9"
1?"
b1 ;"
0@"
1s"
b1 m"
0}"
b11111 o"
1~"
0.#
b1111 *#
1/#
b11000001000111010100010110000001 !
b11000001000111010100010110000001 +
b1100 )#
03#
03
0=
1\
1g
0l
1v
0#"
0B"
1\"
0a"
0f"
0v"
16#
0;#
17
1A
0Q
0V
0p
1u
0'"
0<"
0A"
1`"
1p"
1z"
0+#
00#
1"
b10 .
b1111 G
b1001 a
b110 {
b0 7"
b11 Q"
b1001 k"
b111 '#
b1111 -
b1000 F
b1011 `
b1101 z
b1100 6"
b1110 P"
b111 j"
b100 &#
b1111001001100000110100111110010 &
b1111001001100000110100111110010 *
b1000111111011001101101110001111 %
b1000111111011001101101110001111 )
#160
b1000 (
#170
0s"
0N
0r"
0H
0l"
0##
02#
00
0T"
1}"
0~"
1.#
0/#
1D
0E
0?"
1h"
0i"
0X
0|"
0-#
0C
0>"
0g"
1T
0U
1x
1x"
0y"
0(#
b1101 /
1?
0@
b0 ;"
08"
1c"
0d"
0S
0m
1w
0w"
0n"
0>
bz0000110 ,
0~
0b"
1$
0O
b11000 K
0P
0j
0n
b1001 c
0s
b11101 e
1t
1D"
b1100 S"
0Y"
0t"
b110 m"
0$#
b0 o"
0%#
b0 1
0;
b1010 I
0Y
b1100 }
14"
b1111 !"
05"
b1010 9"
0I"
b0 U"
0_"
b11010110110010101100100110101101 !
b11010110110010101100100110101101 +
b1101 )#
03#
b11100 *#
1>#
13
08
1=
0M
0R
0g
1l
1q
0("
1B"
1L"
0W"
0\"
1a"
1f"
0q"
1v"
0"#
0,#
1;#
02
07
0<
1Q
1V
0f
1'"
01"
0F"
0K"
0["
0`"
0e"
0p"
0u"
1+#
10#
1:#
b101 .
b1100 G
b1110 a
b100 {
b1010 7"
b1100 Q"
b10 k"
b1110 '#
b1000 -
b1110 F
b1010 `
b111 z
b0 6"
b0 P"
b100 j"
b1111 &#
b11100010110010100100111011000101 &
b11100010110010100100111011000101 *
b11110100000000000111101011101000 %
b11110100000000000111101011101000 )
#180
b1001 (
#190
0i
1S
1-#
0h
1P
1(#
0b
1Y"
1s"
0=#
1N
1n"
0J
1M"
1X"
1r"
0<#
1H
1Y
0x
1%#
13#
0_
1J"
1R"
1l"
09#
1:
10
1X
0w
1##
12#
1C
0]
0r
1H"
1:"
bz1110101 ,
1T"
1|"
07#
19
1D
1E
1T
1U
1^
b0 c
0s
0t
1?"
1^"
0c"
1}"
1~"
1.#
1/#
b111 )#
18#
b1011 /
0?
1@
b1110 I
0O
b111 K
0Z
b10000 e
0o
b1000 }
0/"
0D"
1E"
0I"
b1001 9"
1N"
b11100 ;"
1O"
b11 S"
0h"
b10001 U"
1i"
0x"
b11101 o"
1y"
b1110101001110011000000011101011 !
b1110101001110011000000011101011 +
b101 m"
0$#
b10011 *#
04#
16
1B
1R
0W
0\
0l
0q
1#"
1="
1\"
0a"
1{"
1,#
01#
06#
12
1<
1L
0V
0k
0""
0,"
1A"
1F"
1K"
1e"
1u"
1!#
00#
14
b1101 .
b10 G
b1000 a
b101 {
b1011 7"
b1010 Q"
b110 k"
b1001 '#
b1101 -
b1011 F
b1000 `
b10 z
b1110 6"
b1000 P"
b1110 j"
b1101 &#
b11011 1
1'
b10010110101010110101100000101101 &
b10010110101010110101100000101101 *
b11011110100011100010100010111101 %
b11011110100011100010100010111101 )
#200
b1010 (
#210
03"
0N
02#
1x
1/"
00"
1s"
0H
0/#
1w
0."
0>"
1r"
00
0X
0$"
0##
0-#
0:
1t
1*"
0+"
08"
1l"
1?
0E
0U
0|
1D"
1c"
1x"
0~"
0(#
09
1r
0)"
0~
1]"
1g"
1T"
0$
1>
0C
0S
0]
0d
1C"
1b"
1w"
0|"
bz0110000 ,
0n"
07#
06
1T
1i
1o
b1001 c
0s
0%"
0&"
b1110 }
14"
b0 !"
05"
0N"
0Y"
1Z"
1d"
0h"
1i"
1.#
1=#
0>#
1;
0@
b1101 /
1D
0O
0P
1Y
b0 K
0Z
b110 I
0^
b1100 e
0y
b10 9"
0?"
b11110 ;"
1@"
b110 S"
1^"
b11111 U"
1_"
1t"
0y"
1}"
b111 m"
0$#
b11 o"
0%#
13#
b0 *#
04#
b10110111011000101110100101101101 !
b10110111011000101110100101101101 +
b1011 )#
08#
03
18
0=
0R
1g
1l
1q
0v
0#"
0-"
12"
0L"
1W"
1a"
0f"
1q"
0v"
0,#
0;#
17
0<
0A
0L
1V
0[
1k
0u
1,"
1<"
1["
1`"
1p"
0u"
0z"
0!#
10#
05#
04
b1010 .
b0 G
b111 a
b1000 {
b11 7"
b111 Q"
b101 k"
b0 '#
b11 -
b110 F
b10 `
b110 z
b1111 6"
b1110 P"
b1 j"
b1011 &#
b100 1
0'
b101011100111000011100001010 &
b101011100111000011100001010 *
b10110001111011110110001001100011 %
b10110001111011110110001001100011 )
#220
b1011 (
#230
0^"
0]"
1Y"
0Z"
0X"
0R"
0x"
0:"
0w"
1N"
0O"
0x
0t"
0M"
0w
0r"
1I"
0J"
0?
1n
1s
0t
b1100 9"
0D"
b0 o"
0l"
1X
0H"
12#
0>
1m
0r
0C"
bz0000000 ,
0T"
0T
b100 K
1U
1^
b110 }
04"
0E"
0.#
b10 *#
1/#
18#
b1011 /
1:
0;
b1100 I
1Y
b110 c
0i
1j
b10 e
0o
b0 ;"
0@"
b1101 S"
1h"
b1100 U"
0i"
b101 m"
1s"
13#
b1100101110111000110011011001011 !
b1100101110111000110011011001011 +
b110 )#
0=#
1R
1\
0l
1-"
02"
0="
0B"
1L"
1,#
16#
02
07
0V
1f
0k
0,"
0<"
0A"
0K"
0e"
0p"
00#
0:#
14
b1010 G
b101 a
b100 {
b1000 7"
b101 '#
b0 -
b10 F
b1 `
b10 z
b100 6"
b110 P"
b0 j"
b1 &#
b1 1
1'
b1010101011110000100010110101010 &
b1010101011110000100010110101010 *
b10000011001000010000100100000 %
b10000011001000010000100100000 )
#240
b1100 (
#250
1%"
1.#
0x
1$"
0r"
1-#
1C
0w
1|"
1T
1|
0c"
0l"
1(#
1@
b1010 I
0Y
1s
0t
1y"
b101 )#
03#
0#
19
1S
1d
1)"
1."
0b"
0g"
0T"
bz1000100 ,
1n"
1$
1>
0X
0m
0r
1w"
02#
05
16
1D
1P
1y
1&"
1*"
b111 !"
1+"
1/"
b1111 }
14"
1?"
1D"
0N"
0Y"
1^"
0_"
0d"
b1010 S"
1h"
b0 U"
0i"
1}"
1%#
1>#
1:
b1111 1
1;
b1010 /
0?
b10 K
0U
0j
b110 c
1n
b10000 e
0o
b11 9"
0I"
0s"
b10110 o"
1t"
b1010100101000111111011010101010 !
b1010100101000111111011010101010 +
b100 m"
0x"
b10001 *#
0/#
13
0B
1M
0R
0\
0g
0q
1v
1#"
1("
0-"
12"
1="
1B"
0L"
0W"
0\"
0a"
1f"
0{"
1"#
0,#
06#
1;#
17
1<
1L
0Q
1[
0f
1k
1p
1u
1""
0F"
0`"
1p"
1u"
1!#
0+#
15#
1:#
0"
b11 .
b1 G
b1000 a
b1011 {
b11 7"
b1000 Q"
b1001 k"
b1000 '#
b110 -
b1001 F
b1110 `
b11 z
b0 6"
b10 P"
b1011 j"
b1100 &#
b10001001100000111011100000010011 &
b10001001100000111011100000010011 *
b11001011001000000011111010010110 %
b11001011001000000011111010010110 )
#260
b1101 (
